src/main.py
src/tools_old.py
src/builders/basic_t.py
src/builders/cmake_t.py
src/commands/build_next.py
src/commands/clean_next.py
src/commands/config_add.py
src/commands/config_env.py
src/commands/config_get.py
src/commands/config_set.py
src/commands/create_next.py
src/commands/exce_next.py
src/commands/info_next.py
src/commands/run_next.py
src/commands/use_next.py
src/commands/version_next.py
src/funcs/dependencies.py
src/funcs/includes.py
src/funcs/libraries.py
src/funcs/read_config.py
src/funcs/tree.py
src/funcs/write_config.py
src/models/build_t.py
src/models/config_t.py
src/models/dependencie_t.py
src/models/node_t.py
src/models/tree_t.py
src/tool/env.py
src/tool/file.py
src/tool/json.py
src/tool/messages.py
src/tool/os.py
src/tool/string.py
src/tool/types.py
src/tool/yaml.py
next_pm-3.4.0.dist-info/LICENSE
next_pm-3.4.0.dist-info/METADATA
next_pm-3.4.0.dist-info/WHEEL
next_pm-3.4.0.dist-info/entry_points.txt
next_pm-3.4.0.dist-info/top_level.txt
next_pm-3.4.0.dist-info/RECORD
