Metadata-Version: 2.1
Name: next-pm
Version: 3.4.0
Summary: Next is a C/C++ project manager, it is designed as a solution to the administration that this type of projects require.
Home-page: https://github.com/reitmas32/Next
Author: Rafael Zamora
Author-email: rafa.zamora.ram@gmail.com
License: PSF
Keywords: C/C++,package,libraries,developer,manager,dependency,tool,c,c++,cpp
Classifier: Programming Language :: Python :: 3
Classifier: License :: OSI Approved :: Python Software Foundation License
Classifier: Development Status :: 5 - Production/Stable
Classifier: Intended Audience :: Developers
Classifier: Operating System :: OS Independent
Classifier: Topic :: Software Development :: Build Tools
License-File: LICENSE
